kin/__init__.py
kin/account.py
kin/client.py
kin/config.py
kin/errors.py
kin/monitors.py
kin/transactions.py
kin/utils.py
kin/version.py
kin/blockchain/__init__.py
kin/blockchain/channel_manager.py
kin/blockchain/environment.py
kin/blockchain/errors.py
kin/blockchain/horizon_models.py
kin/blockchain/keypair.py
kin/blockchain/utils.py
kin_sdk-2.5.1.dist-info/LICENSE.md
kin_sdk-2.5.1.dist-info/METADATA
kin_sdk-2.5.1.dist-info/WHEEL
kin_sdk-2.5.1.dist-info/top_level.txt
kin_sdk-2.5.1.dist-info/RECORD
