Metadata-Version: 2.1
Name: kin-sdk
Version: 2.5.1
Summary: KIN SDK for Python
Home-page: https://github.com/kinecosystem/kin-sdk-python/tree/v2-master
Author: Kin Ecosystem
Author-email: david.bolshoy@kik.com
Maintainer: Ron Serruya
Maintainer-email: ron.serruya@kik.com
License: MIT
Keywords: kin,stellar,blockchain,cryptocurrency
Platform: UNKNOWN
Classifier: License :: OSI Approved :: MIT License
Classifier: Intended Audience :: Developers
Classifier: Topic :: Software Development :: Libraries :: Python Modules
Classifier: Programming Language :: Python
Classifier: Programming Language :: Python :: 3
Requires-Python: >=3.6
Requires-Dist: kin-base (==1.4.0)
Requires-Dist: schematics (==2.1.*)
Requires-Dist: async-generator; python_version < "3.7"
